{
    "images": [
        {
            "file_name": "arandano_aug_280.jpg",
            "height": 128,
            "width": 128,
            "id": 15
        }
    ],
    "annotations": [
        {
            "id": 1,
            "image_id": 15,
            "category_id": 2,
            "segmentation": [
                [
                    19.11247443762781,
                    54.286298568507156,
                    18.9079754601227,
                    56.33128834355828,
                    18.49897750511247,
                    56.94478527607362,
                    18.29447852760736,
                    58.78527607361963,
                    21.36196319018405,
                    59.60327198364008,
                    22.79345603271983,
                    59.807770961145195,
                    23.61145194274029,
                    58.376278118609406,
                    23.8159509202454,
                    56.535787321063395,
                    23.8159509202454,
                    55.51329243353783,
                    21.56646216768916,
                    54.49079754601227
                ]
            ],
            "area": 30.486657382664028,
            "bbox": [
                18.29447852760736,
                54.286298568507156,
                5.521472392638039,
                5.521472392638039
            ],
            "iscrowd": 0
        },
        {
            "id": 2,
            "image_id": 15,
            "category_id": 2,
            "segmentation": [
                [
                    29.13292433537832,
                    80.46216768916156,
                    27.70143149284253,
                    82.09815950920246,
                    27.70143149284253,
                    82.9161554192229,
                    27.29243353783231,
                    84.75664621676891,
                    28.7239263803681,
                    85.57464212678937,
                    30.155419222903888,
                    85.98364008179959,
                    31.995910020449898,
                    86.39263803680981,
                    33.22290388548058,
                    85.16564417177914,
                    34.44989775051124,
                    83.93865030674847,
                    34.654396728016366,
                    81.89366053169734,
                    34.654396728016366,
                    80.25766871165644,
                    33.01840490797545,
                    78.62167689161554,
                    31.38241308793455,
                    78.62167689161554
                ]
            ],
            "area": 57.20952990327081,
            "bbox": [
                27.29243353783231,
                78.62167689161554,
                7.361963190184056,
                7.770961145194278
            ],
            "iscrowd": 0
        },
        {
            "id": 3,
            "image_id": 15,
            "category_id": 2,
            "segmentation": [
                [
                    80.16541353383458,
                    106.38721804511277,
                    79.41353383458646,
                    106.38721804511277,
                    78.09774436090225,
                    107.1390977443609,
                    77.53383458646616,
                    108.07894736842104,
                    78.28571428571428,
                    109.0187969924812,
                    78.47368421052632,
                    110.3345864661654,
                    81.66917293233082,
                    110.71052631578947,
                    82.60902255639097,
                    109.95864661654134,
                    83.54887218045113,
                    108.64285714285714,
                    83.73684210526315,
                    107.32706766917292
                ]
            ],
            "area": 26.817513709084743,
            "bbox": [
                77.53383458646616,
                106.38721804511277,
                6.203007518796994,
                4.323308270676691
            ],
            "iscrowd": 0
        },
        {
            "id": 4,
            "image_id": 15,
            "category_id": 2,
            "segmentation": [
                [
                    65.69172932330827,
                    85.71052631578947,
                    66.25563909774435,
                    88.34210526315789,
                    68.88721804511277,
                    89.46992481203007,
                    70.9548872180451,
                    88.90601503759397,
                    72.08270676691728,
                    87.21428571428571,
                    72.27067669172932,
                    85.71052631578947,
                    72.45864661654134,
                    84.0187969924812,
                    71.89473684210526,
                    82.89097744360902,
                    68.88721804511277,
                    83.26691729323308,
                    66.81954887218045,
                    83.26691729323308,
                    66.06766917293233,
                    83.83082706766916,
                    66.25563909774435,
                    87.59022556390977
                ]
            ],
            "area": 44.519192718638685,
            "bbox": [
                65.69172932330827,
                82.89097744360902,
                6.766917293233078,
                6.578947368421055
            ],
            "iscrowd": 0
        },
        {
            "id": 5,
            "image_id": 15,
            "category_id": 2,
            "segmentation": [
                [
                    68.32330827067669,
                    58.642857142857146,
                    67.00751879699247,
                    59.77067669172933,
                    66.25563909774435,
                    60.8984962406015,
                    66.63157894736841,
                    62.026315789473685,
                    68.13533834586465,
                    62.026315789473685,
                    70.203007518797,
                    62.026315789473685,
                    71.89473684210526,
                    62.026315789473685,
                    73.21052631578947,
                    61.838345864661655,
                    73.3984962406015,
                    60.52255639097744,
                    73.3984962406015,
                    59.39473684210527
                ]
            ],
            "area": 24.167561761546743,
            "bbox": [
                66.25563909774435,
                58.642857142857146,
                7.142857142857153,
                3.383458646616539
            ],
            "iscrowd": 0
        },
        {
            "id": 6,
            "image_id": 15,
            "category_id": 2,
            "segmentation": [
                [
                    71.14285714285714,
                    58.642857142857146,
                    69.6390977443609,
                    57.890977443609025,
                    73.02255639097744,
                    59.01879699248121,
                    72.8345864661654,
                    62.402255639097746,
                    68.88721804511277,
                    62.026315789473685,
                    67.19548872180451,
                    62.402255639097746
                ]
            ],
            "area": 26.28752331957714,
            "bbox": [
                67.19548872180451,
                57.890977443609025,
                5.8270676691729335,
                4.511278195488721
            ],
            "iscrowd": 0
        },
        {
            "id": 7,
            "image_id": 15,
            "category_id": 2,
            "segmentation": [
                [
                    91.81954887218045,
                    101.68796992481202,
                    88.62406015037594,
                    103.37969924812029,
                    89.0,
                    106.38721804511277,
                    93.69924812030075,
                    107.51503759398496,
                    96.14285714285714,
                    106.76315789473684,
                    97.45864661654134,
                    104.13157894736841,
                    97.45864661654134,
                    101.68796992481202
                ]
            ],
            "area": 51.47973316750519,
            "bbox": [
                88.62406015037594,
                101.68796992481202,
                8.834586466165405,
                5.8270676691729335
            ],
            "iscrowd": 0
        },
        {
            "id": 8,
            "image_id": 15,
            "category_id": 2,
            "segmentation": [
                [
                    100.09022556390975,
                    44.16917293233083,
                    98.77443609022556,
                    46.04887218045113,
                    98.77443609022556,
                    47.92857142857143,
                    100.46616541353383,
                    48.86842105263158,
                    103.47368421052632,
                    48.49248120300752,
                    104.22556390977444,
                    46.98872180451128,
                    104.41353383458646,
                    45.10902255639098,
                    102.1578947368421,
                    43.9812030075188
                ]
            ],
            "area": 27.559500254395356,
            "bbox": [
                98.77443609022556,
                43.9812030075188,
                5.639097744360896,
                4.887218045112782
            ],
            "iscrowd": 0
        },
        {
            "id": 9,
            "image_id": 15,
            "category_id": 2,
            "segmentation": [
                [
                    100.2781954887218,
                    50.184210526315795,
                    100.46616541353383,
                    52.62781954887218,
                    103.09774436090224,
                    52.81578947368421,
                    104.41353383458646,
                    52.43984962406015,
                    105.16541353383458,
                    50.74812030075188,
                    105.16541353383458,
                    49.620300751879704,
                    101.40601503759397,
                    48.49248120300752
                ]
            ],
            "area": 21.128950195036428,
            "bbox": [
                100.2781954887218,
                48.49248120300752,
                4.887218045112775,
                4.323308270676691
            ],
            "iscrowd": 0
        },
        {
            "id": 10,
            "image_id": 15,
            "category_id": 2,
            "segmentation": [
                [
                    103.09774436090224,
                    54.131578947368425,
                    106.10526315789473,
                    56.19924812030075,
                    108.17293233082707,
                    54.695488721804516,
                    109.11278195488721,
                    51.68796992481203,
                    110.9924812030075,
                    50.184210526315795,
                    111.5563909774436,
                    47.7406015037594,
                    108.92481203007519,
                    46.61278195488722,
                    106.10526315789473,
                    46.04887218045113,
                    104.22556390977444,
                    47.17669172932331
                ]
            ],
            "area": 85.85844310023184,
            "bbox": [
                103.09774436090224,
                46.04887218045113,
                8.458646616541358,
                10.150375939849624
            ],
            "iscrowd": 0
        },
        {
            "id": 11,
            "image_id": 15,
            "category_id": 2,
            "segmentation": [
                [
                    96.14285714285714,
                    81.76315789473684,
                    96.89473684210526,
                    83.64285714285714,
                    95.57894736842104,
                    85.71052631578947,
                    94.26315789473684,
                    87.77819548872179,
                    94.6390977443609,
                    88.90601503759397,
                    98.02255639097744,
                    87.21428571428571,
                    102.34586466165412,
                    85.71052631578947,
                    103.47368421052632,
                    81.38721804511277,
                    101.593984962406,
                    79.13157894736841,
                    98.96240601503759,
                    79.13157894736841
                ]
            ],
            "area": 90.02770083102499,
            "bbox": [
                94.26315789473684,
                79.13157894736841,
                9.21052631578948,
                9.774436090225564
            ],
            "iscrowd": 0
        },
        {
            "id": 12,
            "image_id": 15,
            "category_id": 2,
            "segmentation": [
                [
                    97.83458646616542,
                    89.09398496240601,
                    102.7218045112782,
                    89.28195488721803,
                    105.72932330827068,
                    90.2218045112782,
                    108.17293233082707,
                    87.59022556390977,
                    108.36090225563909,
                    85.3345864661654,
                    106.85714285714285,
                    83.4548872180451,
                    105.3533834586466,
                    81.19924812030075,
                    103.84962406015036,
                    81.19924812030075,
                    103.47368421052632,
                    84.0187969924812,
                    103.66165413533834,
                    86.65037593984962,
                    101.21804511278195,
                    86.83834586466165
                ]
            ],
            "area": 94.97427779976243,
            "bbox": [
                97.83458646616542,
                81.19924812030075,
                10.52631578947367,
                9.022556390977442
            ],
            "iscrowd": 0
        },
        {
            "id": 13,
            "image_id": 15,
            "category_id": 2,
            "segmentation": [
                [
                    31.857142857142858,
                    42.47744360902256,
                    29.977443609022554,
                    44.92105263157895,
                    29.977443609022554,
                    46.80075187969925,
                    31.481203007518797,
                    49.808270676691734,
                    34.86466165413533,
                    49.43233082706767,
                    35.992481203007515,
                    46.42481203007519,
                    36.368421052631575,
                    44.16917293233083,
                    36.5563909774436,
                    42.28947368421053,
                    36.368421052631575,
                    39.65789473684211,
                    33.73684210526315,
                    39.46992481203008
                ]
            ],
            "area": 68.01543332014238,
            "bbox": [
                29.977443609022554,
                39.46992481203008,
                6.578947368421044,
                10.338345864661655
            ],
            "iscrowd": 0
        },
        {
            "id": 14,
            "image_id": 15,
            "category_id": 2,
            "segmentation": [
                [
                    74.15037593984962,
                    62.214285714285715,
                    75.84210526315789,
                    63.53007518796993,
                    77.1578947368421,
                    64.46992481203007,
                    78.66165413533834,
                    62.778195488721806,
                    79.0375939849624,
                    60.33458646616541,
                    78.66165413533834,
                    58.078947368421055,
                    77.34586466165413,
                    57.1390977443609,
                    74.71428571428571,
                    57.32706766917293
                ]
            ],
            "area": 35.827350330713934,
            "bbox": [
                74.15037593984962,
                57.1390977443609,
                4.887218045112775,
                7.330827067669169
            ],
            "iscrowd": 0
        },
        {
            "id": 15,
            "image_id": 15,
            "category_id": 2,
            "segmentation": [
                [
                    97.27067669172932,
                    71.80075187969925,
                    99.33834586466163,
                    70.67293233082707,
                    102.53383458646617,
                    70.67293233082707,
                    102.7218045112782,
                    68.79323308270676,
                    102.7218045112782,
                    66.34962406015038,
                    100.46616541353383,
                    65.59774436090225,
                    98.21052631578947,
                    65.2218045112782,
                    96.5187969924812,
                    68.04135338345864
                ]
            ],
            "area": 40.8092599920855,
            "bbox": [
                96.5187969924812,
                65.2218045112782,
                6.203007518796994,
                6.578947368421055
            ],
            "iscrowd": 0
        },
        {
            "id": 16,
            "image_id": 15,
            "category_id": 2,
            "segmentation": [
                [
                    104.22556390977444,
                    71.23684210526315,
                    106.85714285714285,
                    71.80075187969925,
                    108.17293233082707,
                    69.73308270676691,
                    108.73684210526316,
                    68.79323308270676,
                    108.54887218045111,
                    67.47744360902254,
                    107.04511278195487,
                    65.2218045112782,
                    104.41353383458646,
                    64.6578947368421
                ]
            ],
            "area": 32.22341568206239,
            "bbox": [
                104.22556390977444,
                64.6578947368421,
                4.511278195488728,
                7.142857142857153
            ],
            "iscrowd": 0
        }
    ],
    "categories": [
        {
            "id": 1,
            "name": "Biche"
        },
        {
            "id": 2,
            "name": "Rojo"
        },
        {
            "id": 3,
            "name": "Maduro"
        },
        {
            "id": 4,
            "name": "maduro"
        }
    ]
}